ibaqpy/__init__.py
ibaqpy/commands/__init__.py
ibaqpy/commands/datasets_merger.py
ibaqpy/commands/features2peptides.py
ibaqpy/commands/peptides2protein.py
ibaqpy/commands/tsne_visualization.py
ibaqpy/data/__init__.py
ibaqpy/data/data.py
ibaqpy/data/organisms.json
ibaqpy/ibaq/__init__.py
ibaqpy/ibaq/combiner.py
ibaqpy/ibaq/ibaqpy_commons.py
ibaqpy/ibaq/ibaqpy_postprocessing.py
ibaqpy/ibaq/imputation_methods.py
ibaqpy/ibaq/peptide_normalization.py
ibaqpy/ibaq/peptides2protein.py
ibaqpy/ibaq/utils.py
ibaqpy/ibaq/write_queue.py
ibaqpy/ibaqpyc.py
ibaqpy/model/__init__.py
ibaqpy/model/normalization.py
ibaqpy/model/organism_metadata.py
ibaqpy/model/quantification_type.py
ibaqpy-0.0.3.dist-info/LICENSE
ibaqpy-0.0.3.dist-info/METADATA
ibaqpy-0.0.3.dist-info/WHEEL
ibaqpy-0.0.3.dist-info/entry_points.txt
ibaqpy-0.0.3.dist-info/RECORD
