Metadata-Version: 2.3
Name: ibaqpy
Version: 0.0.3
Summary: Python package to compute intensity base absolute expression values
License: MIT
Keywords: quantms,proteomics,mass-spectrometry,data-analysis,big data
Author: Yasset Perez-Riverol
Author-email: ypriverol@gmail.com
Requires-Python: >=3.9
Classifier: Development Status :: 5 - Production/Stable
Classifier: Intended Audience :: Science/Research
Classifier: License :: OSI Approved :: MIT License
Classifier: Operating System :: OS Independent
Classifier: Programming Language :: Python :: 3
Classifier: Programming Language :: Python :: 3.9
Classifier: Programming Language :: Python :: 3.10
Classifier: Programming Language :: Python :: 3.11
Classifier: Programming Language :: Python :: 3.12
Classifier: Programming Language :: Python :: 3.13
Classifier: Programming Language :: Python :: 3 :: Only
Classifier: Topic :: Scientific/Engineering :: Bio-Informatics
Requires-Dist: click
Requires-Dist: duckdb (>=0.10.1)
Requires-Dist: inmoose
Requires-Dist: matplotlib
Requires-Dist: numpy (<2.1.0)
Requires-Dist: pandas
Requires-Dist: pyarrow (>=16.1.0)
Requires-Dist: pyopenms
Requires-Dist: qnorm
Requires-Dist: scikit-learn
Requires-Dist: scipy (>=1.10)
Requires-Dist: seaborn
Requires-Dist: typing_extensions (>=4.6.3)
Project-URL: GitHub, https://github.com/bigbio/ibaqpy/
Project-URL: LICENSE, https://github.com/bigbio/ibaqpy/blob/main/LICENSE
Project-URL: PyPi, https://pypi.org/project/ibaqpy/
Project-URL: Quantms, https://quantms.org
